dh_lottery/__init__.py
dh_lottery/const.py
dh_lottery/dh_lottery.py
dh_lottery/dh_lottery_web.py
dh_lottery/error.py
dh_lottery/model.py
dh_lottery/util.py
dh_lottery-0.0.1.dist-info/LICENSE
dh_lottery-0.0.1.dist-info/METADATA
dh_lottery-0.0.1.dist-info/WHEEL
dh_lottery-0.0.1.dist-info/top_level.txt
dh_lottery-0.0.1.dist-info/RECORD
